pman_tester/__init__.py
pman_tester/p.py
pman_tester-1.0.5.dist-info/METADATA
pman_tester-1.0.5.dist-info/WHEEL
pman_tester-1.0.5.dist-info/entry_points.txt
pman_tester-1.0.5.dist-info/top_level.txt
pman_tester-1.0.5.dist-info/RECORD
