Metadata-Version: 2.1
Name: pman-tester
Version: 1.0.5
Summary: A GUI-based API testing tool
Home-page: https://github.com/tiennsloit/pman
Author: Tien Song Nguyen
Author-email: tiennguyensong@gmail.com
Classifier: Programming Language :: Python :: 3
Classifier: License :: OSI Approved :: MIT License
Classifier: Operating System :: OS Independent
Requires-Python: >=3.6
Requires-Dist: PyQt5 (>=5.15.6)
Requires-Dist: requests (>=2.28.0)
